rofi_pirate/__init__.py
rofi_pirate/cli.py
rofi_pirate/config.py
rofi_pirate/db.py
rofi_pirate/jackett.py
rofi_pirate/magnet.py
rofi_pirate/rofi.py
rofi_pirate/utils.py
rofi_pirate-1.0.1.dist-info/entry_points.txt
rofi_pirate-1.0.1.dist-info/WHEEL
rofi_pirate-1.0.1.dist-info/METADATA
rofi_pirate-1.0.1.dist-info/RECORD
