Metadata-Version: 2.1
Name: rofi-pirate
Version: 1.0.1
Summary: Rofi module for searching torrents using Jackett API.
Home-page: https://github.com/haarnel/rofi-pirate
License: MIT
Author: Pierre Linn
Author-email: haarnel@proton.me
Requires-Python: >=3.10,<4.0
Classifier: License :: OSI Approved :: MIT License
Classifier: Programming Language :: Python :: 3
Classifier: Programming Language :: Python :: 3.10
Requires-Dist: beautifulsoup4 (>=4.11.1,<5.0.0)
Requires-Dist: python-dateutil (>=2.8.2,<3.0.0)
Requires-Dist: requests (>=2.28.1,<3.0.0)
Project-URL: Repository, https://github.com/haarnel/rofi-pirate
